pystrector/__init__.py
pystrector/base_datatypes.py
pystrector/binder.py
pystrector/code_generator/__init__.py
pystrector/code_generator/generate_code.py
pystrector/code_generator/prepare_c_file.py
pystrector/code_generator/staticfiles/prepared_python_structures.c
pystrector/code_generator/staticfiles/python_structures.c
pystrector/code_generator/stream_handler.py
pystrector/core_datatypes.py
pystrector/utils/__init__.py
pystrector/utils/utils.py
pystrector-0.3.2.dist-info/LICENSE
pystrector-0.3.2.dist-info/METADATA
pystrector-0.3.2.dist-info/WHEEL
pystrector-0.3.2.dist-info/RECORD
