Metadata-Version: 2.3
Name: pystrector
Version: 0.3.2
Summary: Python Struct Reflector
License: MIT
Author: bontail
Requires-Python: >=3.12,<4.0
Classifier: License :: OSI Approved :: MIT License
Classifier: Programming Language :: Python :: 3
Classifier: Programming Language :: Python :: 3.12
Classifier: Programming Language :: Python :: 3.13
Requires-Dist: pycparser (>=2.22,<3.0)
